vulcan/__init__.py
vulcan/build_backend.py
vulcan/builder.py
vulcan/cli.py
vulcan/isolation.py
vulcan/plugins.py
vulcan/scripts/__init__.py
vulcan/scripts/setuppy_to_pep621.py
vulcan/scripts/vulcan_1_to_2.py
vulcan_py-2.1.0.dist-info/LICENSE
vulcan_py-2.1.0.dist-info/METADATA
vulcan_py-2.1.0.dist-info/WHEEL
vulcan_py-2.1.0.dist-info/entry_points.txt
vulcan_py-2.1.0.dist-info/top_level.txt
vulcan_py-2.1.0.dist-info/RECORD
