Metadata-Version: 2.1
Name: vulcan-py
Version: 2.1.0
Summary: Tool for leveraging lockfiles to pin dependencies in wheels and sdists
Author-email: Joel Christiansen <joelchristiansen@optiver.com>
License: Apache License Version 2.0
Project-URL: github, https://github.com/optiver/vulcan-py
Keywords: build,tooling
Classifier: Topic :: Software Development :: Build Tools
Classifier: Topic :: Software Development :: Libraries :: Python Modules
Classifier: License :: OSI Approved :: Apache Software License
Requires-Python: >=3.8
License-File: LICENSE
Requires-Dist: setuptools (~=63.0)
Requires-Dist: wheel (~=0.36.2)
Requires-Dist: tomlkit (~=0.11)
Requires-Dist: editables (~=0.5)
Requires-Dist: packaging (~=22.0)
Provides-Extra: cli
Requires-Dist: shiv (~=0.5.2) ; extra == 'cli'
Requires-Dist: build[virtualenv] (~=0.8.0) ; extra == 'cli'
Requires-Dist: click (~=8.0) ; extra == 'cli'
Provides-Extra: convert
Requires-Dist: pkginfo (~=1.9) ; extra == 'convert'
